inteq/__init__.py
inteq/fredholm.py
inteq/helpers.py
inteq/ignore.py
inteq/volterra.py
inteq-0.2.0.dist-info/LICENSE
inteq-0.2.0.dist-info/METADATA
inteq-0.2.0.dist-info/WHEEL
inteq-0.2.0.dist-info/top_level.txt
inteq-0.2.0.dist-info/RECORD
