Metadata-Version: 2.1
Name: inteq
Version: 0.2.0
Summary: Solve various integral equations using numerical methods.
Home-page: https://github.com/mwt/inteq
Author: Matthew Wildrick Thomas
Author-email: matthew.thomas@northwestern.edu
License: MIT License
Project-URL: Bug Tracker, https://github.com/mwt/inteq/issues
Platform: OS Independent
Classifier: Programming Language :: Python :: 3
Classifier: License :: OSI Approved :: MIT License
Classifier: Operating System :: OS Independent
Requires-Python: >=3.4
Requires-Dist: numpy (>=1.7.0)
Requires-Dist: scipy
